ranger_adabelief/__init__.py
ranger_adabelief/ranger_adabelief.py
ranger_adabelief-0.1.0.dist-info/LICENSE.txt
ranger_adabelief-0.1.0.dist-info/METADATA
ranger_adabelief-0.1.0.dist-info/WHEEL
ranger_adabelief-0.1.0.dist-info/top_level.txt
ranger_adabelief-0.1.0.dist-info/RECORD
